setup.py
context111/__init__.py
context111/context333.py
context222/__init__.py
context222/context333.py
simpletestaaa123.egg-info/PKG-INFO
simpletestaaa123.egg-info/SOURCES.txt
simpletestaaa123.egg-info/dependency_links.txt
simpletestaaa123.egg-info/requires.txt
simpletestaaa123.egg-info/top_level.txt