Metadata-Version: 1.0
Name: simpletestaaa123
Version: 0.0.1
Summary: just a simple test
Home-page: UNKNOWN
Author: zhaorr
Author-email: not@all.com
License: MIT License
Keywords: simple,test
Platform: any
